odoo/addons/report_text_format_option/README.rst
odoo/addons/report_text_format_option/__init__.py
odoo/addons/report_text_format_option/__manifest__.py
odoo/addons/report_text_format_option/demo/report_demo.xml
odoo/addons/report_text_format_option/i18n/it.po
odoo/addons/report_text_format_option/i18n/report_text_format_option.pot
odoo/addons/report_text_format_option/models/__init__.py
odoo/addons/report_text_format_option/models/ir_actions_report.py
odoo/addons/report_text_format_option/readme/CONFIGURE.md
odoo/addons/report_text_format_option/readme/DESCRIPTION.md
odoo/addons/report_text_format_option/static/description/icon.png
odoo/addons/report_text_format_option/static/description/index.html
odoo/addons/report_text_format_option/tests/__init__.py
odoo/addons/report_text_format_option/tests/test_report_format_option.py
odoo/addons/report_text_format_option/views/ir_actions_report_views.xml
odoo_addon_report_text_format_option-17.0.1.0.0.2.dist-info/METADATA
odoo_addon_report_text_format_option-17.0.1.0.0.2.dist-info/WHEEL
odoo_addon_report_text_format_option-17.0.1.0.0.2.dist-info/top_level.txt
odoo_addon_report_text_format_option-17.0.1.0.0.2.dist-info/RECORD
