Metadata-Version: 2.1
Name: odoo-addon-report_text_format_option
Version: 17.0.1.0.0.2
Requires-Python: >=3.10
Requires-Dist: odoo>=17.0a,<17.1dev
Summary: Report Text Format Option
Home-page: https://github.com/OCA/reporting-engine
License: LGPL-3
Author: Quartile Limited, Odoo Community Association (OCA)
Author-email: support@odoo-community.org
Classifier: Programming Language :: Python
Classifier: Framework :: Odoo
Classifier: Framework :: Odoo :: 17.0
Classifier: License :: OSI Approved :: GNU Lesser General Public License v3 (LGPLv3)
